extramaths/__init__.py
extramaths/areasolver.py
extramaths/quadsolver.py
extramaths-0.1.0.dist-info/LICENSE.txt
extramaths-0.1.0.dist-info/METADATA
extramaths-0.1.0.dist-info/WHEEL
extramaths-0.1.0.dist-info/top_level.txt
extramaths-0.1.0.dist-info/RECORD
