Metadata-Version: 2.1
Name: extramaths
Version: 0.1.0
Summary: A Python package that simplifies equations.
Home-page: https://github.com/WhenLifeHandsYouLemons/extramaths-python-package
Author: Sooraj Sannabhadti
Author-email: developer.soorajs@gmail.com
License: UNKNOWN
Project-URL: Bug Tracker, https://github.com/WhenLifeHandsYouLemons/extramaths-python-package/issues
Keywords: equations math beginner
Platform: UNKNOWN
Classifier: Programming Language :: Python :: 3
Classifier: License :: OSI Approved :: MIT License
Classifier: Operating System :: OS Independent
Requires-Python: >=3
